[
    {
        "id": "1jh0ftd",
        "author": "D_dawgggg",
        "title": "A king cobra",
        "content": "",
        "upvotes": 23163,
        "comments": 685,
        "media": null,
        "permalink": "/r/interestingasfuck/comments/1jh0ftd/a_king_cobra/"
    },
    {
        "id": "1jh5xf2",
        "author": "VRZcuber14",
        "title": "A phenomenon known as morning glory clouds.",
        "content": "",
        "upvotes": 2258,
        "comments": 37,
        "media": null,
        "permalink": "/r/interestingasfuck/comments/1jh5xf2/a_phenomenon_known_as_morning_glory_clouds/"
    },
    {
        "id": "1jh2fr5",
        "author": "avrock1",
        "title": "The old man attempts to switch kids, so his kid can be paired with the popular athlete Zlatan Ibrahimovi\u0107.",
        "content": "",
        "upvotes": 5465,
        "comments": 99,
        "media": {
            "type": "video",
            "url": "https://v.redd.it/kfpnmm7ds6qe1/DASH_270.mp4?source=fallback"
        },
        "permalink": "/r/interestingasfuck/comments/1jh2fr5/the_old_man_attempts_to_switch_kids_so_his_kid/"
    },
    {
        "id": "1jgzkke",
        "author": "Charming_History7423",
        "title": "This pub in France challenged customers to balance a coin on a lemon in a glass of water for winning a free pint",
        "content": "",
        "upvotes": 9241,
        "comments": 221,
        "media": {
            "type": "video",
            "url": "https://v.redd.it/einna6ssv5qe1/DASH_480.mp4?source=fallback"
        },
        "permalink": "/r/interestingasfuck/comments/1jgzkke/this_pub_in_france_challenged_customers_to/"
    },
    {
        "id": "1jh1x0m",
        "author": "Lastwarfare753",
        "title": "Ice Caves in Iceland.",
        "content": "",
        "upvotes": 3957,
        "comments": 28,
        "media": {
            "type": "image",
            "url": "https://preview.redd.it/59kr38eql6qe1.jpeg?auto=webp&amp;s=77402b3f95793ed0765d7ac059e8e1c200ec6271"
        },
        "permalink": "/r/interestingasfuck/comments/1jh1x0m/ice_caves_in_iceland/"
    },
    {
        "id": "1jgz2w1",
        "author": "_ganjafarian_",
        "title": "Training in the life of a Shaolin monk",
        "content": "",
        "upvotes": 6440,
        "comments": 624,
        "media": {
            "type": "video",
            "url": "https://v.redd.it/oeyls7zvq5qe1/DASH_720.mp4?source=fallback"
        },
        "permalink": "/r/interestingasfuck/comments/1jgz2w1/training_in_the_life_of_a_shaolin_monk/"
    },
    {
        "id": "1jgvio2",
        "author": "RoyalChris",
        "title": "A hailstorm in Australia",
        "content": "",
        "upvotes": 8847,
        "comments": 632,
        "media": {
            "type": "video",
            "url": "https://v.redd.it/5howash6u4qe1/DASH_720.mp4?source=fallback"
        },
        "permalink": "/r/interestingasfuck/comments/1jgvio2/a_hailstorm_in_australia/"
    },
    {
        "id": "1jgusxt",
        "author": "amonaloli12",
        "title": "Transporting the base of a drilling rig. UK, 1980s.",
        "content": "",
        "upvotes": 9796,
        "comments": 96,
        "media": {
            "type": "image",
            "url": "https://preview.redd.it/7e4lumy6o4qe1.jpeg?auto=webp&amp;s=feb131f335bc02d55cbc96c4c90b94de3986a7ad"
        },
        "permalink": "/r/interestingasfuck/comments/1jgusxt/transporting_the_base_of_a_drilling_rig_uk_1980s/"
    },
    {
        "id": "1jgqnz0",
        "author": "Anschuz-3009",
        "title": "Such action is needed against old (500 f*ing year) cruel and gruesome practices that have glorified cruelty for generations",
        "content": "",
        "upvotes": 21679,
        "comments": 669,
        "media": {
            "type": "image",
            "url": "https://preview.redd.it/r7ewih1dr3qe1.png?auto=webp&amp;s=082ae1ed865c36af295ad6867b8d461a62c0ea59"
        },
        "permalink": "/r/interestingasfuck/comments/1jgqnz0/such_action_is_needed_against_old_500_fing_year/"
    },
    {
        "id": "1jh98xt",
        "author": "Nukro666",
        "title": "Oink \ud83d\udc17",
        "content": "",
        "upvotes": 402,
        "comments": 109,
        "media": {
            "type": "video",
            "url": "https://v.redd.it/2xd78dxn09qe1/DASH_720.mp4?source=fallback"
        },
        "permalink": "/r/interestingasfuck/comments/1jh98xt/oink/"
    },
    {
        "id": "1jh54pj",
        "author": "anshuman_17",
        "title": "Two giant sperm-whales protecting a diver from Shark attack (near Mauritius) watch till the end.",
        "content": "",
        "upvotes": 817,
        "comments": 152,
        "media": {
            "type": "video",
            "url": "https://v.redd.it/gvhhcxfjs7qe1/DASH_1080.mp4?source=fallback"
        },
        "permalink": "/r/interestingasfuck/comments/1jh54pj/two_giant_spermwhales_protecting_a_diver_from/"
    },
    {
        "id": "1jgoenr",
        "author": "Docindn",
        "title": "iPhone vs Nokia \ud83d\udcf8",
        "content": "",
        "upvotes": 61498,
        "comments": 1452,
        "media": {
            "type": "video",
            "url": "https://v.redd.it/87jq2baea3qe1/DASH_720.mp4?source=fallback"
        },
        "permalink": "/r/interestingasfuck/comments/1jgoenr/iphone_vs_nokia/"
    },
    {
        "id": "1jgy6uc",
        "author": "occasionallyvertical",
        "title": "invisible Methanol fire at 1981 Indianapolis 500",
        "content": "",
        "upvotes": 2680,
        "comments": 107,
        "media": {
            "type": "video",
            "url": "https://v.redd.it/qncljycai5qe1/DASH_270.mp4?source=fallback"
        },
        "permalink": "/r/interestingasfuck/comments/1jgy6uc/invisible_methanol_fire_at_1981_indianapolis_500/"
    },
    {
        "id": "1jh6b7w",
        "author": "Cool-Fig-9254",
        "title": "Just a zebra crossing",
        "content": "",
        "upvotes": 328,
        "comments": 23,
        "media": {
            "type": "video",
            "url": "https://v.redd.it/id6l5f9g78qe1/DASH_720.mp4?source=fallback"
        },
        "permalink": "/r/interestingasfuck/comments/1jh6b7w/just_a_zebra_crossing/"
    },
    {
        "id": "1jglyfu",
        "author": "Cosie_ODonnell",
        "title": "A perfectly preserved child in a glass coffin was found buried beneath a San Francisco home \u2014 untouched for 145 years",
        "content": "",
        "upvotes": 12448,
        "comments": 273,
        "media": {
            "type": "image",
            "url": "https://external-preview.redd.it/Mib3vEw6nuOHTd8EEIlcO7JSF1tm1GNyBvrVbOiuK_o.jpg?auto=webp&amp;s=043229b9e23e31230714f1dba9e19fd31b0be72a"
        },
        "permalink": "/r/interestingasfuck/comments/1jglyfu/a_perfectly_preserved_child_in_a_glass_coffin_was/"
    },
    {
        "id": "1jh3vbk",
        "author": "4nts",
        "title": "Bailong Elevator",
        "content": "",
        "upvotes": 490,
        "comments": 27,
        "media": {
            "type": "video",
            "url": "https://v.redd.it/08fnarflb7qe1/DASH_1080.mp4?source=fallback"
        },
        "permalink": "/r/interestingasfuck/comments/1jh3vbk/bailong_elevator/"
    },
    {
        "id": "1jgwf0t",
        "author": "bigbusta",
        "title": "An octopus uses its ability to change colors to look like the head of a larger sea creature",
        "content": "",
        "upvotes": 1705,
        "comments": 40,
        "media": {
            "type": "video",
            "url": "https://v.redd.it/bwmghzu325qe1/DASH_720.mp4?source=fallback"
        },
        "permalink": "/r/interestingasfuck/comments/1jgwf0t/an_octopus_uses_its_ability_to_change_colors_to/"
    },
    {
        "id": "1jgjsjv",
        "author": "Sad_Cow_577",
        "title": "Saunas in Finland",
        "content": "",
        "upvotes": 11101,
        "comments": 977,
        "media": {
            "type": "video",
            "url": "https://v.redd.it/tv5ie9hzb2qe1/DASH_720.mp4?source=fallback"
        },
        "permalink": "/r/interestingasfuck/comments/1jgjsjv/saunas_in_finland/"
    },
    {
        "id": "1jh29hk",
        "author": "pauldliteralgreat",
        "title": "Frazier, Foreman, and Ali",
        "content": "",
        "upvotes": 414,
        "comments": 8,
        "media": {
            "type": "image",
            "url": "https://preview.redd.it/vcb762u2q6qe1.jpeg?auto=webp&amp;s=bcd33c3c1bdefbefe8637ce069a578bd5f9584be"
        },
        "permalink": "/r/interestingasfuck/comments/1jh29hk/frazier_foreman_and_ali/"
    },
    {
        "id": "1jh1v8u",
        "author": "hacipuput",
        "title": "Explanation how Chris Lemons a saturation diver survived 35 minutes without oxygen at almost 300 feet below the North Sea.",
        "content": "",
        "upvotes": 410,
        "comments": 37,
        "media": {
            "type": "video",
            "url": "https://v.redd.it/tl9x75e5l6qe1/DASH_480.mp4?source=fallback"
        },
        "permalink": "/r/interestingasfuck/comments/1jh1v8u/explanation_how_chris_lemons_a_saturation_diver/"
    },
    {
        "id": "1jggapv",
        "author": "VRZcuber14",
        "title": "A phenomenon known as \"Volcanic lightning\"",
        "content": "",
        "upvotes": 14552,
        "comments": 124,
        "media": null,
        "permalink": "/r/interestingasfuck/comments/1jggapv/a_phenomenon_known_as_volcanic_lightning/"
    },
    {
        "id": "1jh0tx3",
        "author": "Thunder-Cloud-987",
        "title": "A heat activated Christmas card",
        "content": "",
        "upvotes": 497,
        "comments": 11,
        "media": {
            "type": "video",
            "url": "https://v.redd.it/clsjiujv86qe1/DASH_720.mp4?source=fallback"
        },
        "permalink": "/r/interestingasfuck/comments/1jh0tx3/a_heat_activated_christmas_card/"
    },
    {
        "id": "1jhc1uq",
        "author": "CG_17_LIFE",
        "title": "The 'energy drink' that's full of energy!",
        "content": "",
        "upvotes": 62,
        "comments": 18,
        "media": {
            "type": "video",
            "url": "https://v.redd.it/35ep8l68n9qe1/DASH_1080.mp4?source=fallback"
        },
        "permalink": "/r/interestingasfuck/comments/1jhc1uq/the_energy_drink_thats_full_of_energy/"
    },
    {
        "id": "1jh6vay",
        "author": "ChandlerBingsSarcasm",
        "title": "Two giant sperm whales protect diver from terrifying shark",
        "content": "",
        "upvotes": 127,
        "comments": 50,
        "media": {
            "type": "video",
            "url": "https://v.redd.it/txytlhpud8qe1/DASH_720.mp4?source=fallback"
        },
        "permalink": "/r/interestingasfuck/comments/1jh6vay/two_giant_sperm_whales_protect_diver_from/"
    },
    {
        "id": "1jgzj86",
        "author": "Smart_Search1509",
        "title": "My wife's ball python being a... ball.",
        "content": "",
        "upvotes": 509,
        "comments": 24,
        "media": {
            "type": "image",
            "url": "https://preview.redd.it/h1fbcy7fv5qe1.jpeg?auto=webp&amp;s=ff794e8ebcf0b8dc96a09246cf3d50909aba6586"
        },
        "permalink": "/r/interestingasfuck/comments/1jgzj86/my_wifes_ball_python_being_a_ball/"
    },
    {
        "id": "1jgclzj",
        "author": "SmallAchiever",
        "title": "In 2006, a Coca-Cola employee offered to sell company secrets to Pepsi for 1.5 million dollars. Pepsi responded by notifying Coca-Cola",
        "content": "",
        "upvotes": 54291,
        "comments": 977,
        "media": {
            "type": "image",
            "url": "https://preview.redd.it/zpu742die0qe1.jpeg?auto=webp&amp;s=337503b13dd1fb9563e4fa1ec2373449edcd631a"
        },
        "permalink": "/r/interestingasfuck/comments/1jgclzj/in_2006_a_cocacola_employee_offered_to_sell/"
    },
    {
        "id": "1jggoap",
        "author": "AdSpecialist6598",
        "title": "Five years ago, Clara Daly helped a man who was both deaf and blind  on a flight taking and hour or more to help him have his needs met and getting to know him.",
        "content": "",
        "upvotes": 5760,
        "comments": 253,
        "media": {
            "type": "image",
            "url": "https://preview.redd.it/suu7ip19n1qe1.png?auto=webp&amp;s=88c1952e44ded09f5b03468d644a9502b461a071"
        },
        "permalink": "/r/interestingasfuck/comments/1jggoap/five_years_ago_clara_daly_helped_a_man_who_was/"
    },
    {
        "id": "1jgi7q9",
        "author": "Master_Support",
        "title": "China Great Green wall Project",
        "content": "",
        "upvotes": 3002,
        "comments": 226,
        "media": {
            "type": "video",
            "url": "https://v.redd.it/n1ps5auzz1qe1/DASH_720.mp4?source=fallback"
        },
        "permalink": "/r/interestingasfuck/comments/1jgi7q9/china_great_green_wall_project/"
    },
    {
        "id": "1jgctn1",
        "author": "a1oner_bvcksn6",
        "title": "Otter uses momentum to reach its meal that got stuck high up on the wall",
        "content": "",
        "upvotes": 9158,
        "comments": 53,
        "media": {
            "type": "video",
            "url": "https://v.redd.it/gmen7y1gh0qe1/DASH_720.mp4?source=fallback"
        },
        "permalink": "/r/interestingasfuck/comments/1jgctn1/otter_uses_momentum_to_reach_its_meal_that_got/"
    },
    {
        "id": "1jgnyy4",
        "author": "bigbusta",
        "title": "A moose bluff charges a stupid tourist",
        "content": "",
        "upvotes": 1196,
        "comments": 237,
        "media": {
            "type": "video",
            "url": "https://v.redd.it/26m7nf6573qe1/DASH_480.mp4?source=fallback"
        },
        "permalink": "/r/interestingasfuck/comments/1jgnyy4/a_moose_bluff_charges_a_stupid_tourist/"
    }
]