[
    {
        "id": "1tg4abq",
        "author": "AutoModerator",
        "title": "Megathread: The Crash",
        "content": "Moving forward, let\u2019s keep the discussion about this documentary here. New posts will be deleted.\n\nPlease read the rules. Disrespectful comments will be held for review and may be removed.\n\nThank you.\n\n---\n\nWant to discuss on Discord? Use https://discord.gg/Netflix",
        "upvotes": 382,
        "comments": 4359,
        "media": null,
        "permalink": "/r/netflix/comments/1tg4abq/megathread_the_crash/"
    },
    {
        "id": "1trqumg",
        "author": "Sinnn-_-",
        "title": "Netflix\u2019s Apex Hits 105 Million Views in 24 Days as Charlize Theron and Taron Egerton Thriller Surges Up Charts",
        "content": "",
        "upvotes": 241,
        "comments": 44,
        "media": null,
        "permalink": "/r/netflix/comments/1trqumg/netflixs_apex_hits_105_million_views_in_24_days/"
    },
    {
        "id": "1ts31ox",
        "author": "breanne0_0",
        "title": "Psychological thrillers",
        "content": "Please recommend psychological thriller series from Netflix, I have nothing to watch this weekend except From and Euphoria \n\nMy favorite kind of psychological thrillers are the small town ones where everything seems perfect but if you look closely, dundundun... ",
        "upvotes": 14,
        "comments": 15,
        "media": null,
        "permalink": "/r/netflix/comments/1ts31ox/psychological_thrillers/"
    },
    {
        "id": "1tqz7c8",
        "author": "Sinnn-_-",
        "title": "The Crash Is Blowing Up on Netflix With 27 Million Views in a Week",
        "content": "",
        "upvotes": 1962,
        "comments": 621,
        "media": null,
        "permalink": "/r/netflix/comments/1tqz7c8/the_crash_is_blowing_up_on_netflix_with_27/"
    },
    {
        "id": "1trw0cp",
        "author": "Sinnn-_-",
        "title": "Stranger Things Dominates 2025\u201326 TV Ratings With 32.9M Viewers as Netflix Takes Over Nielsen\u2019s Top Charts",
        "content": "",
        "upvotes": 28,
        "comments": 11,
        "media": null,
        "permalink": "/r/netflix/comments/1trw0cp/stranger_things_dominates_202526_tv_ratings_with/"
    },
    {
        "id": "1trucrr",
        "author": "Sinnn-_-",
        "title": "Netflix Launches \u2018Instadocs\u2019 With Real-Time Documentary on Alex Murdaugh Case Reversal",
        "content": "",
        "upvotes": 25,
        "comments": 2,
        "media": null,
        "permalink": "/r/netflix/comments/1trucrr/netflix_launches_instadocs_with_realtime/"
    },
    {
        "id": "1trnqq0",
        "author": "EquipmentOwn9014",
        "title": "The Boroughs - People need whimsy",
        "content": "I just finished the boroughs after binging it for a couple days and genuinely ended with tears in my eyes. Yes, like people are saying the writing is a bit cheesy at times, but not at all bad. I feel the characters were well flushed out and the topic of coping with dying and grief was interestingly dealt with. Reading people tearing it apart because they didn\u2019t get answers to every single question they have is actually crazy, it\u2019s bound to have another season. Also, maybe suspend your belief for one second? have a little fun? \n\nI don\u2019t know, this is reddit so people will obviously hate and hate and hate into this endless void \ud83d\udc80, but no one else thought it was a fun watch?? ",
        "upvotes": 65,
        "comments": 18,
        "media": null,
        "permalink": "/r/netflix/comments/1trnqq0/the_boroughs_people_need_whimsy/"
    },
    {
        "id": "1tr7pje",
        "author": "Sinnn-_-",
        "title": "Stephen King Calls Netflix\u2019s The Boroughs \u201cAn Absolute Delight\u201d as Sci-Fi Thriller Climbs Charts",
        "content": "",
        "upvotes": 252,
        "comments": 39,
        "media": null,
        "permalink": "/r/netflix/comments/1tr7pje/stephen_king_calls_netflixs_the_boroughs_an/"
    },
    {
        "id": "1tryxd1",
        "author": "gekm12",
        "title": "Lost in the stars",
        "content": "What starts as a simple mystery quickly turns into a rollercoaster of shocking plot twists. \ud83d\ude31 The suspense keeps you hooked from start to finish, making you question who can really be trusted. The ending gets a bit wild, but overall it\u2019s a highly entertaining thriller. **8.5/10 \u2014 definitely worth watching!** \ud83c\udf7f\ud83d\udd25",
        "upvotes": 2,
        "comments": 2,
        "media": null,
        "permalink": "/r/netflix/comments/1tryxd1/lost_in_the_stars/"
    },
    {
        "id": "1trmj76",
        "author": "reddddyornot",
        "title": "Mystery Shows/Movies",
        "content": "Besides Stranger Things and the Knives Out movies, what are some good mystery shows or movies you\u2019d recommend on Netflix? Thanks for any recommendations! ",
        "upvotes": 8,
        "comments": 11,
        "media": null,
        "permalink": "/r/netflix/comments/1trmj76/mystery_showsmovies/"
    },
    {
        "id": "1ts0e36",
        "author": "Sinnn-_-",
        "title": "Netflix Turns to AI Innovation and Wonka Brand Deals to Cut Costs and Boost Growth",
        "content": "",
        "upvotes": 0,
        "comments": 1,
        "media": null,
        "permalink": "/r/netflix/comments/1ts0e36/netflix_turns_to_ai_innovation_and_wonka_brand/"
    },
    {
        "id": "1trm3bc",
        "author": "A-Ginja-Ninja",
        "title": "How many times do I need to watch Halo for it to get picked up for a Third Season?",
        "content": "How many times do I need to watch Halo for it to get picked up for a Third Season? Just finished Season 2 for the second time. The flood is spreading and we need Master Chief!",
        "upvotes": 6,
        "comments": 15,
        "media": null,
        "permalink": "/r/netflix/comments/1trm3bc/how_many_times_do_i_need_to_watch_halo_for_it_to/"
    },
    {
        "id": "1trwi07",
        "author": "Original_Capital4532",
        "title": "I thought they got rid of casting",
        "content": "I noticed when I upgraded my plan I can see the cast button and I thought they originally removed the feature to able to cast to smart tvs and streaming devices such as chrome cast etc as newer streaming devices have remotes ",
        "upvotes": 0,
        "comments": 2,
        "media": null,
        "permalink": "/r/netflix/comments/1trwi07/i_thought_they_got_rid_of_casting/"
    },
    {
        "id": "1trnta3",
        "author": "jumbohotdog___",
        "title": "Need recommendations",
        "content": "What shows/movie/anime would you recommend. i prefer sci-fi or fantasy especially ones that involves powers or op mc. Im also open to other genre but not horror pls\ud83e\udd23",
        "upvotes": 3,
        "comments": 6,
        "media": null,
        "permalink": "/r/netflix/comments/1trnta3/need_recommendations/"
    },
    {
        "id": "1tqyhlz",
        "author": "SquareNo5496",
        "title": "lord of the flies",
        "content": "i'm happy this got a reboot because I love the story, but wow dude I don't know how many more avant garde film gimmicks I can take anymore. each shot is like 30 seconds a piece, which would be fine once in a while but every minute its another and another. it makes the pacing unbearably slow. some people will surely blame this on my gen-z attention span and sure, maybe. but what are you actually doing as a director filming a close up of a kids face for 45 seconds with no dialogue and barely any music, ALLL to pay off to: NOTHING. no payoff! just wanted to look at his face i guess! i'm sure the directors like \"capturing the boys slowly turning feral\" yea, nah. this is EPISODE ONE and there was one shot of just straight up water for like a full minute. No joke. I was in disbelief i had to skip through it i was so bored. ",
        "upvotes": 45,
        "comments": 68,
        "media": null,
        "permalink": "/r/netflix/comments/1tqyhlz/lord_of_the_flies/"
    },
    {
        "id": "1trix3b",
        "author": "bas3adi",
        "title": "Just finished Haunted Hotel and Mating Season. Are there any other adult cartoons similar to these styles?",
        "content": "Just something to turn my brain off while watching. I don\u2019t mind raunchy, as I also just finished Mating Season. Both styles are fine, but I don\u2019t care for Rick &amp; Morty or Bobs Burgers types. Thanks again!",
        "upvotes": 4,
        "comments": 8,
        "media": null,
        "permalink": "/r/netflix/comments/1trix3b/just_finished_haunted_hotel_and_mating_season_are/"
    },
    {
        "id": "1tqcdyd",
        "author": "peoplemagazine",
        "title": "Keanu Reeves Asks for 'Leniency and Mercy' in Upcoming Sentencing of Director Who Was Convicted of Stealing $11 Million from Netflix",
        "content": "",
        "upvotes": 517,
        "comments": 192,
        "media": null,
        "permalink": "/r/netflix/comments/1tqcdyd/keanu_reeves_asks_for_leniency_and_mercy_in/"
    },
    {
        "id": "1trobtp",
        "author": "jfr2810",
        "title": "Using Netflix for Vietnam to Australia flight",
        "content": "Hey, I have a basic ad included Australian Netflix account and had some movies downloaded for my flights to and from Vietnam.\n\nIm flying home tomorrow and wanted to download some more, it wouldn't let me use Netflix because it says the ad version isn't available in Vietnam. It also deleted all the movies I had downloaded.\n\nIf I upgrade beyond ad plan for a month will it let me download some more stuff whilst in Vietnam? I don't mind paying a bit more but don't want to and then find out it doesn't work.\n\nThanks",
        "upvotes": 0,
        "comments": 3,
        "media": null,
        "permalink": "/r/netflix/comments/1trobtp/using_netflix_for_vietnam_to_australia_flight/"
    },
    {
        "id": "1tro4h7",
        "author": "Sufficient_Ebb_5694",
        "title": "What are some genuinely amazing Netflix series?",
        "content": "Im looking for shows that will grab me in the first episode, and make me interested in what happens next. Hopefully throughout the whole series. Some of my favorites are Altered Carbon S1, Brand New Cherry Flavor, all the Mike Flanagan shows and Blue Eye Samurai. Im also enjoying The Blacklist quite a bit. But most of the time, I fall off a show quickly. Any awesome recommendations would be amazing.  Ive already tried Dark like 5 times and it is just too slow for me. It also just might not be my kind of story. It seems a little TOO complex. I dont want to have to take notes or keep track on the website to understand whats going on in a tv show lol",
        "upvotes": 1,
        "comments": 35,
        "media": null,
        "permalink": "/r/netflix/comments/1tro4h7/what_are_some_genuinely_amazing_netflix_series/"
    },
    {
        "id": "1trmp0d",
        "author": "visiny",
        "title": "What in the adhd is netflix's recent 1.5x speed feature when you press on the screen? Am I supposed to constantly enter and exit lock mode just to watch on my phone or tablet?",
        "content": "Please dear God someone tell netflix to disable that stupid 1.5x speed when you press on the screen without me having to constantly enter lock mode (which disables everything, includeing pause, not just the speed up press thing). Why is enshitification something these companies are so insistent on? Maybe it's a subtle way to tell me I shouldn't watch Netflix shows anymore, should do something more constructive... hmm...\n\nNo seriously where are smartphone or tablet users supposed to rest their thumb, if the slightest touch immediately activates the 1.5x speed. Even with youtube, as shitty as they were when they forced the 2x speed press thing, I was able to develop a work around where if I slide my thumb instead of rest my thumb on the side of the screen, it doesn't trigger the automatic 2x speed press thing. But netflix, efficient assholes that they are, somehow accounted for this so even the thumb slide I do for youtube still triggers the 1.5x speed press on Netflix.\n\nThis bothers me because I watch stuff in 1 minute, 2 minute bursts. I'm not going to enter lock mode every fucking time for 1 minute bursts 12 times a day over a 24 hour period, every day, forever. It's honestly infuriating that I now have to reevaluate how I use the app and forced to make a real decision over unsubscribing forever. \n\nIs anyone else even just mild annoyed by this? Because I know that certain people I know in real life from a certain generation do watch stuff 1.5x speed and 2x speed and as someone older I don't really go for that, but to have Netflix not even have a full disable in the app settings rather than just rely on lock everytime just hampers the entire individual watching experience",
        "upvotes": 0,
        "comments": 1,
        "media": null,
        "permalink": "/r/netflix/comments/1trmp0d/what_in_the_adhd_is_netflixs_recent_15x_speed/"
    },
    {
        "id": "1ts2luc",
        "author": "MisterHole123",
        "title": "I barely watch Netflix anymore because (may surprise you)",
        "content": "So. While I am not a big fan of the Netflix esthetic I can sometimes overlook it but... Lately I just can't stomach anymore. For 2 reasons \n\n1. Your series are too damm long (and not episodic they are the same very long story across multiple episodes),  \u200b1h episode = short movie. Series is 45mn or less. The reason series exist is so you don't have to commit to watching hours of it in 1 go. \n\n2. I prefer older movies or series. ",
        "upvotes": 0,
        "comments": 14,
        "media": null,
        "permalink": "/r/netflix/comments/1ts2luc/i_barely_watch_netflix_anymore_because_may/"
    },
    {
        "id": "1tq99sy",
        "author": "NerfTheHighground",
        "title": "Can they stop recommending me stuff I have already watched",
        "content": "It is so annoying that my page is literally full of shows/movies I have already seen. Like how hard it is to have an option to hide stuff you have rated or marked as watched?",
        "upvotes": 282,
        "comments": 27,
        "media": null,
        "permalink": "/r/netflix/comments/1tq99sy/can_they_stop_recommending_me_stuff_i_have/"
    },
    {
        "id": "1trijgt",
        "author": "cOcOBEEEN",
        "title": "Something very bad is going to happen location",
        "content": "Hi, I just watched Something very bad is going to happen and I really liked the house/cabin (?) where the majority of it is filmed, does anyone know where it is or what it\u2019s called? I tried googling it but couldn\u2019t find anything. ",
        "upvotes": 0,
        "comments": 1,
        "media": null,
        "permalink": "/r/netflix/comments/1trijgt/something_very_bad_is_going_to_happen_location/"
    },
    {
        "id": "1trdby8",
        "author": "s_amk4",
        "title": "Help! Can\u2019t figure out how to sign it out",
        "content": "Alright for some reason I can\u2019t put pictures in this subreddit?? But anyways my family reactivated their Netflix account so I would like to use it. However, my personal one (that I canceled Netflix on) is still logged in. When I redownloaded the app it said \u201ctap below to restart Netflix\u201d. Below was a box that takes you to Netflix account manager. How do I fix this? I need to sign out of it, please help ASAP!!",
        "upvotes": 1,
        "comments": 3,
        "media": null,
        "permalink": "/r/netflix/comments/1trdby8/help_cant_figure_out_how_to_sign_it_out/"
    },
    {
        "id": "1trcu2e",
        "author": "Status_Study4204",
        "title": "What happend to the guy on the New BTK documentary??",
        "content": "Hi, first post on this sub. \n\nI am watching the new documentary from 2025 about BTK. One of the guys they are interviewing has a swollen eye and a big band aid on the side of his head. Does anyone know what happend to him? It looks serious..\n\nThank you ",
        "upvotes": 0,
        "comments": 6,
        "media": null,
        "permalink": "/r/netflix/comments/1trcu2e/what_happend_to_the_guy_on_the_new_btk_documentary/"
    },
    {
        "id": "1trmozf",
        "author": "Mother_Bird2",
        "title": "Baby Reindeer/Half Man",
        "content": "For those who watched Baby Reindeer, check out Half Man. Not available on Netflix yet. I'd love recommendations on other shows like them. \n\nIncredible acting. \ud83d\udc4c",
        "upvotes": 0,
        "comments": 15,
        "media": null,
        "permalink": "/r/netflix/comments/1trmozf/baby_reindeerhalf_man/"
    },
    {
        "id": "1tpxaxy",
        "author": "Sinnn-_-",
        "title": "Netflix Warns Germany\u2019s New Law Could Mean Fewer Shows and Movies",
        "content": "",
        "upvotes": 443,
        "comments": 119,
        "media": null,
        "permalink": "/r/netflix/comments/1tpxaxy/netflix_warns_germanys_new_law_could_mean_fewer/"
    },
    {
        "id": "1tqmsy9",
        "author": "gem1803",
        "title": "Homicide: New York",
        "content": "Never been a fan of crime show, just stumbled upon it. I love the latest season, the officers and detectives in the show are so professional and seems to genuinely care about what their job and the feelings of the victims and their families, just makes me want to keep watching. I hope there\u2019s a season 3, five episodes are simply not enough!",
        "upvotes": 16,
        "comments": 13,
        "media": null,
        "permalink": "/r/netflix/comments/1tqmsy9/homicide_new_york/"
    },
    {
        "id": "1tr43kp",
        "author": "bucking_fitch_",
        "title": "Using Netflix account at same time as my parents but in different locations(states away)?",
        "content": "Hi!\n\nI'm traveling across the country for two months, and I am wondering if I will still be able to use my family's shared Netflix account while I'm gone. It's just my parents and me, so we regularly use this account at home, but I'm going to be living out of the house for a while, and I am hoping I can use the same account through my computer. Does anyone have any idea what Netflix's deal with this situation is? Should I do anything before I leave? I have never watched Netflix on my computer before, but I am logged into my family account already.",
        "upvotes": 0,
        "comments": 12,
        "media": null,
        "permalink": "/r/netflix/comments/1tr43kp/using_netflix_account_at_same_time_as_my_parents/"
    },
    {
        "id": "1tr3cl5",
        "author": "Electrical-Mango-839",
        "title": "King of Beggars",
        "content": "The protagonist of the story has become a powerful figure in Hong Kong. He started his career with comedies, and later gradually took on the roles of director and producer, developing a unique style of humor and creative system.",
        "upvotes": 0,
        "comments": 1,
        "media": null,
        "permalink": "/r/netflix/comments/1tr3cl5/king_of_beggars/"
    }
]